<proc name="la_126_ch1">

  <steps>
    <serial_number>
      <text>ID Device:</text>
    </serial_number>

    <multiplot name="multiplot">
      <file_plot>multiplot la_126 ch1.png</file_plot>
      <folder_sweep>
        <var>sweep 126 G5</var>
        <var>sweep 126 G10</var>
      </folder_sweep>
      <!-- <config>
        <plot>
          <y_limit>
            <min>-3.5</min>
            <max>0.5</max>
          </y_limit>
        </plot>
      </config> -->
    </multiplot>

    <multiplot name="multiplot">
      <file_plot>multiplot la_126 ch1 expanded.png</file_plot>
      <folder_sweep>
        <var>sweep 126 G5</var>
        <var>sweep 126 G10</var>
      </folder_sweep>
      <config>
        <plot>
          <y_limit>
            <min>-1.2</min>
            <max>0.2</max>
          </y_limit>
        </plot>
      </config>
    </multiplot>

  </steps>
</proc>